{"uuids": {"phone_id": "13590fc5-3460-4d4e-8ba8-32ac9eece6c3", "uuid": "7247acec-603a-40d7-bf21-555866501928", "client_session_id": "8c1e62bf-98fe-44cc-9895-8bffb5794e7f", "advertising_id": "08b11a52-7bfa-453c-b890-f5a9e9716f28", "android_device_id": "android-2bdbfd401891cbf4", "request_id": "197ef2d1-2c8f-432c-a295-f26cf7c48405", "tray_session_id": "75ffc4d3-8d21-4310-acc8-e8d4dde6ac0b"}, "mid": "aNrgZQABAAGlHxUMe5dYC1_4OT54", "ig_u_rur": null, "ig_www_claim": null, "authorization_data": {"ds_user_id": "76014924225", "sessionid": "76014924225%3AmjYKhLGMssjnsi%3A26%3AAYidrXR0BcBbA-AppMJGkEeftVsHfycV7gyY5RmcOw"}, "cookies": {}, "last_login": 1759174778.4097972, "device_settings": {"app_version": "269.0.0.18.75", "android_version": 26, "android_release": "8.0.0", "dpi": "480dpi", "resolution": "1080x1920", "manufacturer": "OnePlus", "device": "devitron", "model": "6T Dev", "cpu": "qcom", "version_code": "314665256"}, "user_agent": "Instagram 269.0.0.18.75 Android (30/11; 450dpi; 1080x2340; OnePlus/OnePlus; OnePlus 6T Dev; OnePlus 6T; qcom; en_US; 449904927)", "country": "US", "country_code": 1, "locale": "en_US", "timezone_offset": -14400}